objecttoclass.py
objecttoclass-0.0.1.dist-info/LICENCE
objecttoclass-0.0.1.dist-info/METADATA
objecttoclass-0.0.1.dist-info/WHEEL
objecttoclass-0.0.1.dist-info/top_level.txt
objecttoclass-0.0.1.dist-info/RECORD
