Metadata-Version: 2.1
Name: objecttoclass
Version: 0.0.1
Summary: Simple Python script to convert a dict into a class instance 
Author: Hussein Naim
License: UNKNOWN
Platform: UNKNOWN
Classifier: Programming Language :: Python :: 3
Classifier: License :: OSI Approved :: MIT License
Classifier: Operating System :: OS Independent
Requires-Python: >=3.6
License-File: LICENCE
